soccer_poisson/soccer_pro.py
soccer_poisson-0.1.17.dist-info/METADATA
soccer_poisson-0.1.17.dist-info/WHEEL
soccer_poisson-0.1.17.dist-info/top_level.txt
soccer_poisson-0.1.17.dist-info/RECORD
