Metadata-Version: 2.1
Name: soccer-poisson
Version: 0.1.17
Summary: poisson calcs for soccer
Home-page: https://github.com/larssl780/soccer
Author: larssl780
Author-email: slick.stash.0m@icloud.com
License: MIT
Classifier: License :: OSI Approved :: MIT License
Classifier: Programming Language :: Python :: 3
Classifier: Programming Language :: Python :: 3.7
